czech_workdays_holidays.py
czech_workdays_holidays-0.1.11.dist-info/LICENSE
czech_workdays_holidays-0.1.11.dist-info/METADATA
czech_workdays_holidays-0.1.11.dist-info/WHEEL
czech_workdays_holidays-0.1.11.dist-info/top_level.txt
czech_workdays_holidays-0.1.11.dist-info/RECORD
