Metadata-Version: 2.1
Name: czech-workdays-holidays
Version: 0.1.11
Summary: Czech Workdays, Holidays and Shopping Days
Author-email: David Gamba <gamba.d@seznam.cz>
Project-URL: Homepage, https://github.com/david-gamba/Czech-Working-Days
Project-URL: Bug Tracker, https://github.com/david-gamba/Czech-Working-Days/issues
Classifier: Programming Language :: Python :: 3
Classifier: License :: OSI Approved :: MIT License
Classifier: Operating System :: OS Independent
Requires-Python: >=3.8
License-File: LICENSE
Requires-Dist: python-dateutil (>=2.8.2)
Requires-Dist: six (>=1.16.0)
